az_automl_helper/__init__.py
az_automl_helper/helper.py
az_automl_helper-0.2.dist-info/LICENSE
az_automl_helper-0.2.dist-info/METADATA
az_automl_helper-0.2.dist-info/WHEEL
az_automl_helper-0.2.dist-info/top_level.txt
az_automl_helper-0.2.dist-info/RECORD
