Metadata-Version: 2.1
Name: az_automl_helper
Version: 0.2
Summary: A helper library for Azure AutoML solutions
Home-page: https://github.com/kitranet/az_automl_helper
Author: Microsoft Corporation
Author-email: support@microsoft.com
Maintainer: M.R. Vijay Krishnan
Maintainer-email: vijaykrishnanmr@gmail.com
License: MIT
Classifier: Programming Language :: Python :: 3
Classifier: License :: OSI Approved :: MIT License
Classifier: Operating System :: OS Independent
License-File: LICENSE
Requires-Dist: azureml-core
